README.md
setup.py
textwarden/__init__.py
textwarden/__main__.py
textwarden/commands.py
textwarden/config.py
textwarden/database.py
textwarden/tools.py
textwarden/users.py
textwarden.egg-info/PKG-INFO
textwarden.egg-info/SOURCES.txt
textwarden.egg-info/dependency_links.txt
textwarden.egg-info/entry_points.txt
textwarden.egg-info/requires.txt
textwarden.egg-info/top_level.txt