Metadata-Version: 2.1
Name: textwarden
Version: 0.0.1
Summary: Generic Discord bot.
Home-page: https://gitlab.com/nul.one/textwarden
Author: Predrag Mandic
Author-email: predrag@nul.one
License: BSD
Download-URL: https://gitlab.com/nul.one/textwarden/-/archive/0.0.1/textwarden-0.0.1.tar.gz
Platform: UNKNOWN
Classifier: Development Status :: 4 - Beta
Classifier: Environment :: Console
Classifier: License :: OSI Approved :: BSD License
Classifier: Natural Language :: English
Classifier: Operating System :: POSIX :: Linux
Classifier: Programming Language :: Python :: 3 :: Only
Classifier: Topic :: Utilities
Requires-Python: >=3.4.6
